WebChannel/__init__.py
WebChannel/audio/__init__.py
WebChannel/video/__init__.py
test/__init__.py
WebChannel-2023.9.1.dist-info/LICENSE.txt
WebChannel-2023.9.1.dist-info/METADATA
WebChannel-2023.9.1.dist-info/WHEEL
WebChannel-2023.9.1.dist-info/top_level.txt
WebChannel-2023.9.1.dist-info/RECORD
